.VERSION
AUTHORS.rst
CONTRIBUTING.rst
HISTORY.rst
LICENSE
MANIFEST.in
Pipfile
Pipfile.lock
README.rst
USAGE.rst
dev-requirements.txt
requirements.txt
setup.cfg
setup.py
docs/Makefile
docs/authors.rst
docs/conf.py
docs/contributing.rst
docs/hashivaultlib.rst
docs/history.rst
docs/index.rst
docs/installation.rst
docs/modules.rst
docs/readme.rst
docs/usage.rst
hashivaultlib/.VERSION
hashivaultlib/AUTHORS.rst
hashivaultlib/CONTRIBUTING.rst
hashivaultlib/HISTORY.rst
hashivaultlib/LICENSE
hashivaultlib/Pipfile
hashivaultlib/Pipfile.lock
hashivaultlib/README.rst
hashivaultlib/USAGE.rst
hashivaultlib/__init__.py
hashivaultlib/_version.py
hashivaultlib/dev-requirements.txt
hashivaultlib/hashivaultlib.py
hashivaultlib/hashivaultlibexceptions.py
hashivaultlib/requirements.txt
hashivaultlib.egg-info/PKG-INFO
hashivaultlib.egg-info/SOURCES.txt
hashivaultlib.egg-info/dependency_links.txt
hashivaultlib.egg-info/not-zip-safe
hashivaultlib.egg-info/requires.txt
hashivaultlib.egg-info/top_level.txt
hashivaultlib/__pycache__/__init__.cpython-37.pyc
hashivaultlib/__pycache__/_version.cpython-37.pyc
hashivaultlib/__pycache__/hashivaultlib.cpython-37.pyc
hashivaultlib/__pycache__/hashivaultlibexceptions.cpython-37.pyc
tests/test_hashivaultlib.py