Metadata-Version: 2.1
Name: hashivaultlib
Version: 1.4.1
Summary: An extension to hvac, implementing recursive removal and retrieval of secrets and models for tokens and policies.
Home-page: https://github.com/schubergphilis/hashivaultlib.git
Author: Costas Tyfoxylos
Author-email: ctyfoxylos@schubergphilis.com
License: MIT
Keywords: hashivaultlib hashicorp vault
Classifier: Development Status :: 4 - Beta
Classifier: Intended Audience :: Developers
Classifier: License :: OSI Approved :: MIT License
Classifier: Natural Language :: English
Classifier: Programming Language :: Python :: 3.7
License-File: LICENSE
License-File: AUTHORS.rst
Requires-Dist: hvac~=2.3.0; python_version >= "3.8" and python_version < "4.0"
Requires-Dist: dateutils~=0.6.12
Requires-Dist: pyhcl~=0.4.5
